jupylite_duckdb/__init__.py
jupylite_duckdb/_version.py
jupylite_duckdb/jdw.py
jupylite_duckdb/jdw_magic.py
jupylite_duckdb/magic.py
jupylite_duckdb-0.0.17.dist-info/LICENSE
jupylite_duckdb-0.0.17.dist-info/METADATA
jupylite_duckdb-0.0.17.dist-info/WHEEL
jupylite_duckdb-0.0.17.dist-info/top_level.txt
jupylite_duckdb-0.0.17.dist-info/RECORD
