Metadata-Version: 2.1
Name: jupylite-duckdb
Version: 0.0.17
Summary: Testing
Home-page: https://github.com/iqmo-org/
Author: iqmo
Author-email: info@iqmo.com
Keywords: jupyterlite duckdb wasm
License-File: LICENSE
Requires-Dist: pandas
Requires-Dist: nbformat (>=4.2.0)
Requires-Dist: ipywidgets
